{
  "lead_score": 57.0,
  "tier": "Medium",
  "key_observations": [
    "Parklane has 64 open leasing and property management job postings, which signals serious staffing strain. Lead with the angle that EliseAI reduces dependence on headcount by automating the repetitive communication layer, so the rep should frame this as a way to do more with the team they already have rather than waiting for hiring to catch up.",
    "Resident reviews surface maintenance responsiveness and unit condition at move-in as recurring friction points. These are exactly the workflows EliseAI addresses through automated maintenance intake and move-in communication, so the rep can position EliseAI as a way to create a more consistent resident experience without adding staff burden.",
    "Boise is showing strong income growth at 11.7% year over year alongside steady population gains, which means demand is healthy but competition for quality residents is real. The rep should emphasize that 24/7 lead engagement and faster follow-up directly improve lease conversion in a market where prospects have options and response time matters."
  ],
  "market_fit": 65.79,
  "company_fit": 38.89,
  "person_fit": 19.05,
  "building_fit": 0.0,
  "signals": [
    {
      "name": "Job Postings",
      "category": "Company",
      "points": 12.0,
      "max_points": 12.0,
      "reason": "Multiple active job postings found. Company is hiring and actively growing."
    },
    {
      "name": "Renter Rate",
      "category": "Market",
      "points": 8.0,
      "max_points": 8.0,
      "reason": "High share of housing is renter-occupied. Strong property management market."
    },
    {
      "name": "Renter-Occupied Units",
      "category": "Market",
      "points": 7.5,
      "max_points": 15.0,
      "reason": "Moderate rental market by unit count. Partial score based on size tier."
    },
    {
      "name": "Portfolio / Web Presence",
      "category": "Company",
      "points": 6.0,
      "max_points": 8.0,
      "reason": "Strong web presence with a verified Google Knowledge Graph entry. Established brand."
    },
    {
      "name": "Yelp Rating vs. Market",
      "category": "Company",
      "points": 6.0,
      "max_points": 6.0,
      "reason": "Yelp rating is notably below the local market average. Strong resident pain signal."
    },
    {
      "name": "Economic Momentum",
      "category": "Market",
      "points": 5.0,
      "max_points": 5.0,
      "reason": "Strong year-over-year income growth. Healthy economic trajectory for the city."
    },
    {
      "name": "Corporate Email",
      "category": "Person",
      "points": 4.0,
      "max_points": 4.0,
      "reason": "Email uses a verified company domain. Contact legitimacy confirmed."
    },
    {
      "name": "Population Growth YoY",
      "category": "Market",
      "points": 2.5,
      "max_points": 5.0,
      "reason": "Stable population growth. Steady market conditions."
    },
    {
      "name": "Social Media Presence",
      "category": "Company",
      "points": 2.5,
      "max_points": 5.0,
      "reason": "Some social media presence detected."
    },
    {
      "name": "Median Gross Rent",
      "category": "Market",
      "points": 2.0,
      "max_points": 5.0,
      "reason": "Median rent falls in the mid range, representing an average US rental market."
    },
    {
      "name": "Resident Pain Themes",
      "category": "Company",
      "points": 1.5,
      "max_points": 5.0,
      "reason": "Some resident complaint themes identified from Yelp or web reviews."
    },
    {
      "name": "Tech Stack",
      "category": "Company",
      "points": 0.0,
      "max_points": 8.0,
      "reason": "No tech stack data. BuiltWith key not configured or no tools detected."
    },
    {
      "name": "Employee Count",
      "category": "Company",
      "points": 0.0,
      "max_points": 8.0,
      "reason": "Company is below the minimum headcount threshold or LinkedIn data is unavailable."
    },
    {
      "name": "Company Age",
      "category": "Company",
      "points": 0.0,
      "max_points": 5.0,
      "reason": "Early-stage company or no founding year data is available."
    },
    {
      "name": "Portfolio Size",
      "category": "Company",
      "points": 0.0,
      "max_points": 6.0,
      "reason": "No portfolio size data could be extracted."
    },
    {
      "name": "Google Rating",
      "category": "Company",
      "points": 0.0,
      "max_points": 4.0,
      "reason": "No Google rating data available or rating is above the scoring threshold."
    },
    {
      "name": "Competitor Rank (Yelp)",
      "category": "Company",
      "points": 0.0,
      "max_points": 5.0,
      "reason": "No competitor data available or company ranks well relative to competitors."
    },
    {
      "name": "Contact Seniority",
      "category": "Person",
      "points": 0.0,
      "max_points": 10.0,
      "reason": "No seniority data from PDL or contact is below the decision-maker threshold."
    },
    {
      "name": "Department / Function",
      "category": "Person",
      "points": 0.0,
      "max_points": 7.0,
      "reason": "No department data available or contact is outside the property management function."
    },
    {
      "name": "Building Yelp Rating",
      "category": "Building",
      "points": 0.0,
      "max_points": 8.0,
      "reason": "No building Yelp data available or the building is well-rated."
    },
    {
      "name": "Building Review Volume",
      "category": "Building",
      "points": 0.0,
      "max_points": 4.0,
      "reason": "Low review count or no building Yelp data is available."
    },
    {
      "name": "Building Price Tier",
      "category": "Building",
      "points": 0.0,
      "max_points": 4.0,
      "reason": "No price tier data from Yelp or the building is at the budget tier."
    },
    {
      "name": "Building Pain Themes",
      "category": "Building",
      "points": 0.0,
      "max_points": 4.0,
      "reason": "No building-level complaint themes were extracted from reviews."
    }
  ]
}